x_net_django_email_template/__init__.py
x_net_django_email_template/locale/x_net_django_email_template/locale/LC_MESSAGES/django.po
x_net_django_email_template/static/css/email/html-email.min.css
x_net_django_email_template/static/css/email/html-email.min.css.map
x_net_django_email_template/static/img/email/color_header.png
x_net_django_email_template/static/img/email/logo.png
x_net_django_email_template/static_src/scss/email/.stylelintrc.json
x_net_django_email_template/static_src/scss/email/_container.scss
x_net_django_email_template/static_src/scss/email/_media-query.scss
x_net_django_email_template/static_src/scss/email/_normalize.scss
x_net_django_email_template/static_src/scss/email/_typography.scss
x_net_django_email_template/static_src/scss/email/_utils.scss
x_net_django_email_template/static_src/scss/email/_variables.scss
x_net_django_email_template/static_src/scss/email/html-email.scss
x_net_django_email_template/static_src/scss/email/components/_button.scss
x_net_django_email_template/static_src/scss/email/components/_image.scss
x_net_django_email_template/static_src/scss/email/sections/_footer.scss
x_net_django_email_template/static_src/scss/email/sections/_header.scss
x_net_django_email_template/static_src/scss/email/sections/_main.scss
x_net_django_email_template/templates/email/base.html
x_net_django_email_template/templates/email/default.html
x_net_django_email_template/templatetags/__init__.py
x_net_django_email_template/templatetags/html_email.py
x_net_django_email_template-1.0.3.dist-info/LICENSE
x_net_django_email_template-1.0.3.dist-info/METADATA
x_net_django_email_template-1.0.3.dist-info/WHEEL
x_net_django_email_template-1.0.3.dist-info/top_level.txt
x_net_django_email_template-1.0.3.dist-info/RECORD
