Metadata-Version: 2.1
Name: x-net-django-email-template
Version: 1.0.3
Summary: An Email HTML template for Django
Home-page: https://github.com/x-net-services/x-net-django-email-template
Author: X-Net Services GmbH
Author-email: support-software@x-net.at
License: MIT
Platform: UNKNOWN
Classifier: Framework :: Django :: 2.2
Classifier: License :: OSI Approved :: MIT License
Classifier: Programming Language :: Python :: 3.6
Classifier: Topic :: Internet :: WWW/HTTP
Requires-Python: >=3.6
